abaqus2py/__init__.py
abaqus2py/_src/__init__.py
abaqus2py/_src/abaqus_simulator.py
abaqus2py/_src/f3dasm_adapter.py
abaqus2py/_src/io.py
abaqus2py-1.1.0.dist-info/licenses/LICENSE
abaqus2py-1.1.0.dist-info/METADATA
abaqus2py-1.1.0.dist-info/WHEEL
abaqus2py-1.1.0.dist-info/top_level.txt
abaqus2py-1.1.0.dist-info/RECORD
